djversion/__init__.py
djversion/apps.py
djversion/conf.py
djversion/context_processors.py
djversion/rest.py
djversion/urls.py
djversion/utils.py
djversion/locale/en/LC_MESSAGES/django.mo
djversion/locale/en/LC_MESSAGES/django.po
djversion/locale/uk/LC_MESSAGES/django.mo
djversion/locale/uk/LC_MESSAGES/django.po
djversion/management/__init__.py
djversion/management/commands/__init__.py
djversion/management/commands/print-version.py
djversion/templatetags/__init__.py
djversion/templatetags/djversion_tags.py
django_project_version-0.19.0.dist-info/METADATA
django_project_version-0.19.0.dist-info/MIT-LICENSE
django_project_version-0.19.0.dist-info/WHEEL
django_project_version-0.19.0.dist-info/top_level.txt
django_project_version-0.19.0.dist-info/RECORD
