Metadata-Version: 2.1
Name: django-project-version
Version: 0.19.0
Summary: Django reusable app to show your project version
Home-page: https://github.com/DCOD-OpenSource/django-project-version/
Author: DCOD
Author-email: contact@d-cod.com
License: MIT
Keywords: django,version,project,django-project-version
Classifier: Development Status :: 5 - Production/Stable
Classifier: Environment :: Plugins
Classifier: Framework :: Django :: 3.2
Classifier: Framework :: Django :: 4.0
Classifier: Framework :: Django :: 4.1
Classifier: Framework :: Django :: 4.2
Classifier: Framework :: Django :: 5.0
Classifier: License :: OSI Approved :: MIT License
Classifier: Operating System :: Unix
Classifier: Programming Language :: Python :: 3.8
Classifier: Programming Language :: Python :: 3.9
Classifier: Programming Language :: Python :: 3.10
Classifier: Programming Language :: Python :: 3.11
Classifier: Topic :: Utilities
License-File: MIT-LICENSE
Requires-Dist: django <5.1,>=3.2
Requires-Dist: django-appconf >=1.0.3
Provides-Extra: git
Requires-Dist: gitpython >=3.0.2 ; extra == 'git'
Provides-Extra: rest
Requires-Dist: djangorestframework >=3.10.3 ; extra == 'rest'
Provides-Extra: test
Requires-Dist: attrs ==23.2.0 ; extra == 'test'
Requires-Dist: autoflake ==2.2.1 ; extra == 'test'
Requires-Dist: bandit ==1.7.6 ; extra == 'test'
Requires-Dist: black ==23.12.1 ; extra == 'test'
Requires-Dist: check-manifest ==0.49 ; extra == 'test'
Requires-Dist: check-wheel-contents ==0.6.0 ; extra == 'test'
Requires-Dist: coverage ==6.5.0 ; extra == 'test'
Requires-Dist: coveralls ==3.3.1 ; extra == 'test'
Requires-Dist: curlylint ==0.13.1 ; extra == 'test'
Requires-Dist: darglint ==1.8.1 ; extra == 'test'
Requires-Dist: dennis ==1.1.0 ; extra == 'test'
Requires-Dist: django-stubs ==4.2.7 ; extra == 'test'
Requires-Dist: djangorestframework-stubs ==3.14.5 ; extra == 'test'
Requires-Dist: dlint ==0.14.1 ; extra == 'test'
Requires-Dist: dodgy ==0.2.1 ; extra == 'test'
Requires-Dist: dotenv-linter ==0.4.0 ; extra == 'test'
Requires-Dist: flake8-annotations-complexity ==0.0.8 ; extra == 'test'
Requires-Dist: flake8-annotations-coverage ==0.0.6 ; extra == 'test'
Requires-Dist: flake8-blind-except ==0.2.1 ; extra == 'test'
Requires-Dist: flake8-boolean-trap ==1.0.1 ; extra == 'test'
Requires-Dist: flake8-broken-line ==1.0.0 ; extra == 'test'
Requires-Dist: flake8-bugbear ==23.12.2 ; extra == 'test'
Requires-Dist: flake8-builtins ==2.2.0 ; extra == 'test'
Requires-Dist: flake8-coding ==1.3.2 ; extra == 'test'
Requires-Dist: flake8-cognitive-complexity ==0.1.0 ; extra == 'test'
Requires-Dist: flake8-comprehensions ==3.14.0 ; extra == 'test'
Requires-Dist: flake8-datetimez ==20.10.0 ; extra == 'test'
Requires-Dist: flake8-debugger ==4.1.2 ; extra == 'test'
Requires-Dist: flake8-django ==1.4 ; extra == 'test'
Requires-Dist: flake8-docstrings ==1.7.0 ; extra == 'test'
Requires-Dist: flake8-eradicate ==1.5.0 ; extra == 'test'
Requires-Dist: flake8-executable ==2.1.3 ; extra == 'test'
Requires-Dist: flake8-expression-complexity ==0.0.11 ; extra == 'test'
Requires-Dist: flake8-fixme ==1.1.1 ; extra == 'test'
Requires-Dist: flake8-functions ==0.0.8 ; extra == 'test'
Requires-Dist: flake8-gettext ==0.0.0.1 ; extra == 'test'
Requires-Dist: flake8-logging-format ==0.9.0 ; extra == 'test'
Requires-Dist: flake8-mutable ==1.2.0 ; extra == 'test'
Requires-Dist: flake8-no-implicit-concat ==0.3.5 ; extra == 'test'
Requires-Dist: flake8-no-pep420 ==2.7.0 ; extra == 'test'
Requires-Dist: flake8-pie ==0.16.0 ; extra == 'test'
Requires-Dist: flake8-print ==5.0.0 ; extra == 'test'
Requires-Dist: flake8-raise ==0.0.5 ; extra == 'test'
Requires-Dist: flake8-return ==1.2.0 ; extra == 'test'
Requires-Dist: flake8-self ==0.2.2 ; extra == 'test'
Requires-Dist: flake8-simplify ==0.21.0 ; extra == 'test'
Requires-Dist: flake8-spellcheck ==0.28.0 ; extra == 'test'
Requires-Dist: flake8-super ==0.1.3 ; extra == 'test'
Requires-Dist: flake8-tidy-imports ==4.10.0 ; extra == 'test'
Requires-Dist: flake8-todos ==0.3.0 ; extra == 'test'
Requires-Dist: flake8-typing-imports ==1.15.0 ; extra == 'test'
Requires-Dist: flake8-use-fstring ==1.4 ; extra == 'test'
Requires-Dist: flake8-use-pathlib ==0.3.0 ; extra == 'test'
Requires-Dist: flake8-variables-names ==0.0.6 ; extra == 'test'
Requires-Dist: flake8 ==6.0.0 ; extra == 'test'
Requires-Dist: flynt ==1.0.1 ; extra == 'test'
Requires-Dist: importlib-metadata ==7.0.1 ; extra == 'test'
Requires-Dist: interrogate ==1.5.0 ; extra == 'test'
Requires-Dist: isort ==5.13.2 ; extra == 'test'
Requires-Dist: mypy ==1.8.0 ; extra == 'test'
Requires-Dist: pep8-naming ==0.13.3 ; extra == 'test'
Requires-Dist: perflint ==0.7.3 ; extra == 'test'
Requires-Dist: pip-outdated ==0.6.0 ; extra == 'test'
Requires-Dist: polint ==0.4 ; extra == 'test'
Requires-Dist: pre-commit-hooks ==4.5.0 ; extra == 'test'
Requires-Dist: pre-commit ==3.5.0 ; extra == 'test'
Requires-Dist: pygments ==2.17.2 ; extra == 'test'
Requires-Dist: pylint-django ==2.5.5 ; extra == 'test'
Requires-Dist: pylint ==2.17.4 ; extra == 'test'
Requires-Dist: pyroma ==4.2 ; extra == 'test'
Requires-Dist: pytest-cov ==4.1.0 ; extra == 'test'
Requires-Dist: pytest-django ==4.7.0 ; extra == 'test'
Requires-Dist: pytest-extra-durations ==0.1.3 ; extra == 'test'
Requires-Dist: pytest-instafail ==0.5.0 ; extra == 'test'
Requires-Dist: pytest-sugar ==0.9.7 ; extra == 'test'
Requires-Dist: pytest-timer[termcolor] ==1.00 ; extra == 'test'
Requires-Dist: pytest ==7.4.4 ; extra == 'test'
Requires-Dist: pymarkdownlnt ==0.9.15 ; extra == 'test'
Requires-Dist: readme-renderer ==42.0 ; extra == 'test'
Requires-Dist: removestar ==1.5 ; extra == 'test'
Requires-Dist: rstcheck ==6.2.0 ; extra == 'test'
Requires-Dist: seed-isort-config ==2.2.0 ; extra == 'test'
Requires-Dist: tabulate ==0.9.0 ; extra == 'test'
Requires-Dist: tox-gh-actions ==3.2.0 ; extra == 'test'
Requires-Dist: tox ==4.11.4 ; extra == 'test'
Requires-Dist: twine ==4.0.2 ; extra == 'test'
Requires-Dist: tryceratops ==2.3.2 ; extra == 'test'
Requires-Dist: wheel ==0.42.0 ; extra == 'test'
Requires-Dist: yesqa ==1.5.0 ; extra == 'test'
